{
  "thresholds": {
    "codingCompletionRate": 0.9,
    "validationSuccessRate": 0.9,
    "gitCloseoutSuccessRate": 1,
    "maxAvoidableTakeoverRate": 0.2
  },
  "metrics": {
    "codingCompletionRate": 1,
    "validationSuccessRate": 1,
    "repairSuccessRate": 0,
    "gitCloseoutSuccessRate": 1,
    "endToEndCompletionRate": 0.8666666666666667,
    "closureCompletionRate": 0,
    "meanStepsToClosure": 7.83,
    "meanRepairsToClosure": 0,
    "avoidableTakeoverRate": 0,
    "desktopCompletionRate": 1,
    "desktopWrongTargetTotal": 0,
    "desktopTimeoutCount": 0,
    "qualityGateBlockedTotal": 0
  },
  "latency": {
    "thresholds": {
      "chatFirstToolImprovement": 0.3,
      "codingTotalRunImprovement": 0.15,
      "desktopElapsedImprovement": 0.2
    },
    "baselineAvailable": false,
    "baseline": null,
    "current": {
      "laneMedians": {
        "chat": {
          "count": 1,
          "ttfrMs": 5,
          "firstToolMs": null,
          "firstVisibleMs": 5,
          "totalRunMs": 15352,
          "elapsedMs": 15717
        },
        "browser": {
          "count": 1,
          "ttfrMs": 4,
          "firstToolMs": 9620,
          "firstVisibleMs": 9620,
          "totalRunMs": 23705,
          "elapsedMs": 26119
        },
        "desktop": {
          "count": 6,
          "ttfrMs": 4,
          "firstToolMs": 13985,
          "firstVisibleMs": 13985,
          "totalRunMs": 41342,
          "elapsedMs": 43061
        },
        "coding": {
          "count": 6,
          "ttfrMs": 4,
          "firstToolMs": 13792,
          "firstVisibleMs": 13792,
          "totalRunMs": 65761.5,
          "elapsedMs": 67501.5
        }
      },
      "chatProbeCount": 1,
      "browserProbeCount": 1,
      "desktopProbeCount": 6,
      "codingTargetCount": 2,
      "medianChatTtfrMs": 5,
      "medianChatFirstToolMs": 5,
      "medianBrowserElapsedMs": 26119,
      "medianCodingElapsedMs": 67501.5,
      "medianCodingTotalRunMs": 65761.5,
      "medianDesktopElapsedMs": 43061,
      "medianFallbackCount": 0
    },
    "chatFirstToolImprovement": null,
    "codingTotalRunImprovement": null,
    "desktopElapsedImprovement": null,
    "passing": true,
    "failingReasons": []
  },
  "codingLaneCoverage": {
    "repo_scaffold": {
      "total": 1,
      "completed": 1
    },
    "single_file_edit": {
      "total": 1,
      "completed": 1
    },
    "multi_file_feature_delivery": {
      "total": 2,
      "completed": 2
    },
    "validation_repair": {
      "total": 1,
      "completed": 1
    },
    "git_closeout": {
      "total": 1,
      "completed": 1
    }
  },
  "passing": true,
  "failingReasons": []
}
